objector/__init__.py
objector-2020.11.0a1.dist-info/LICENSE
objector-2020.11.0a1.dist-info/WHEEL
objector-2020.11.0a1.dist-info/METADATA
objector-2020.11.0a1.dist-info/RECORD
