Metadata-Version: 2.1
Name: objector
Version: 2020.11.0a1
Summary: Object recursion, mapping, and iteration tools
Home-page: https://github.com/whardier/objector
License: MIT
Author: Shane R. Spencer
Author-email: 305301+whardier@users.noreply.github.com
Requires-Python: >=3.8,<4.0
Classifier: License :: OSI Approved :: MIT License
Classifier: Programming Language :: Python :: 3
Classifier: Programming Language :: Python :: 3.8
Classifier: Programming Language :: Python :: 3.9
Project-URL: Funding, https://github.com/sponsors/whardier
Project-URL: Repository, https://github.com/whardier/objector
